python_lbp3/__init__.py
python_lbp3/auth.py
python_lbp3/endpoints.py
python_lbp3/exceptions.py
python_lbp3/objects.py
python_lbp3/sync.py
python_lbp3-0.1.0.dist-info/LICENSE
python_lbp3-0.1.0.dist-info/WHEEL
python_lbp3-0.1.0.dist-info/METADATA
python_lbp3-0.1.0.dist-info/RECORD
