Metadata-Version: 2.1
Name: python-lbp3
Version: 0.1.0
Summary: A Python API wrapper for the LBP3 datastore
License: MIT
Author: Matt Gosden
Author-email: mdgosden@gmail.com
Requires-Python: >=3.6,<4.0
Classifier: License :: OSI Approved :: MIT License
Classifier: Programming Language :: Python :: 3
Classifier: Programming Language :: Python :: 3.6
Classifier: Programming Language :: Python :: 3.7
Classifier: Programming Language :: Python :: 3.8
Classifier: Programming Language :: Python :: 3.9
Requires-Dist: backoff (>=1.10.0,<2.0.0)
Requires-Dist: httpx
